[
	{
		"C":"HH",
		"Y":2019,
		"N":92.0,
		"O":134.0
	},
	{
		"C":"HH",
		"Y":2020,
		"N":94.0,
		"O":134.0
	},
	{
		"C":"HH",
		"Y":2021,
		"N":95.0,
		"O":135.0
	},
	{
		"C":"HH",
		"Y":2022,
		"N":98.0,
		"O":135.0
	},
	{
		"C":"HH",
		"Y":2023,
		"N":99.0,
		"O":136.0
	},
	{
		"C":"HH",
		"Y":2024,
		"N":101.0,
		"O":136.0
	},
	{
		"C":"HH",
		"Y":2025,
		"N":102.0,
		"O":137.0
	},
	{
		"C":"HH",
		"Y":2026,
		"N":103.0,
		"O":137.0
	},
	{
		"C":"HH",
		"Y":2027,
		"N":104.0,
		"O":138.0
	},
	{
		"C":"HH",
		"Y":2028,
		"N":104.0,
		"O":138.0
	},
	{
		"C":"HH",
		"Y":2029,
		"N":104.0,
		"O":138.0
	},
	{
		"C":"HH",
		"Y":2030,
		"N":105.0,
		"O":139.0
	},
	{
		"C":"HH",
		"Y":2031,
		"N":111.0,
		"O":139.0
	},
	{
		"C":"HH",
		"Y":2032,
		"N":122.0,
		"O":139.0
	},
	{
		"C":"HH",
		"Y":2033,
		"N":128.0,
		"O":140.0
	},
	{
		"C":"HH",
		"Y":2034,
		"N":138.0,
		"O":141.0
	},
	{
		"C":"HH",
		"Y":2035,
		"N":152.0,
		"O":142.0
	},
	{
		"C":"HH",
		"Y":2036,
		"N":163.0,
		"O":142.0
	},
	{
		"C":"HH",
		"Y":2037,
		"N":171.0,
		"O":142.0
	},
	{
		"C":"HH",
		"Y":2038,
		"N":178.0,
		"O":143.0
	},
	{
		"C":"HH",
		"Y":2039,
		"N":183.0,
		"O":145.0
	},
	{
		"C":"HH",
		"Y":2040,
		"N":190.0,
		"O":146.0
	},
	{
		"C":"HH",
		"Y":2041,
		"N":204.0,
		"O":147.0
	},
	{
		"C":"HH",
		"Y":2042,
		"N":213.0,
		"O":147.0
	},
	{
		"C":"HH",
		"Y":2043,
		"N":224.0,
		"O":148.0
	},
	{
		"C":"HH",
		"Y":2044,
		"N":230.0,
		"O":149.0
	},
	{
		"C":"HH",
		"Y":2045,
		"N":235.0,
		"O":148.0
	},
	{
		"C":"HH",
		"Y":2046,
		"N":224.0,
		"O":149.0
	},
	{
		"C":"HH",
		"Y":2047,
		"N":232.0,
		"O":151.0
	},
	{
		"C":"HH",
		"Y":2048,
		"N":220.0,
		"O":152.0
	},
	{
		"C":"HH",
		"Y":2049,
		"N":225.0,
		"O":153.0
	},
	{
		"C":"HH",
		"Y":2050,
		"N":212.0,
		"O":155.0
	},
	{
		"C":"POP",
		"Y":2019,
		"N":230.0,
		"O":334.0
	},
	{
		"C":"POP",
		"Y":2020,
		"N":235.0,
		"O":333.0
	},
	{
		"C":"POP",
		"Y":2021,
		"N":236.0,
		"O":333.0
	},
	{
		"C":"POP",
		"Y":2022,
		"N":240.0,
		"O":332.0
	},
	{
		"C":"POP",
		"Y":2023,
		"N":244.0,
		"O":331.0
	},
	{
		"C":"POP",
		"Y":2024,
		"N":245.0,
		"O":331.0
	},
	{
		"C":"POP",
		"Y":2025,
		"N":245.0,
		"O":330.0
	},
	{
		"C":"POP",
		"Y":2026,
		"N":246.0,
		"O":329.0
	},
	{
		"C":"POP",
		"Y":2027,
		"N":246.0,
		"O":328.0
	},
	{
		"C":"POP",
		"Y":2028,
		"N":245.0,
		"O":327.0
	},
	{
		"C":"POP",
		"Y":2029,
		"N":246.0,
		"O":326.0
	},
	{
		"C":"POP",
		"Y":2030,
		"N":245.0,
		"O":325.0
	},
	{
		"C":"POP",
		"Y":2031,
		"N":258.0,
		"O":324.0
	},
	{
		"C":"POP",
		"Y":2032,
		"N":286.0,
		"O":324.0
	},
	{
		"C":"POP",
		"Y":2033,
		"N":300.0,
		"O":324.0
	},
	{
		"C":"POP",
		"Y":2034,
		"N":325.0,
		"O":325.0
	},
	{
		"C":"POP",
		"Y":2035,
		"N":364.0,
		"O":326.0
	},
	{
		"C":"POP",
		"Y":2036,
		"N":387.0,
		"O":328.0
	},
	{
		"C":"POP",
		"Y":2037,
		"N":404.0,
		"O":328.0
	},
	{
		"C":"POP",
		"Y":2038,
		"N":419.0,
		"O":331.0
	},
	{
		"C":"POP",
		"Y":2039,
		"N":429.0,
		"O":335.0
	},
	{
		"C":"POP",
		"Y":2040,
		"N":444.0,
		"O":337.0
	},
	{
		"C":"POP",
		"Y":2041,
		"N":477.0,
		"O":338.0
	},
	{
		"C":"POP",
		"Y":2042,
		"N":498.0,
		"O":339.0
	},
	{
		"C":"POP",
		"Y":2043,
		"N":526.0,
		"O":340.0
	},
	{
		"C":"POP",
		"Y":2044,
		"N":540.0,
		"O":341.0
	},
	{
		"C":"POP",
		"Y":2045,
		"N":551.0,
		"O":340.0
	},
	{
		"C":"POP",
		"Y":2046,
		"N":527.0,
		"O":345.0
	},
	{
		"C":"POP",
		"Y":2047,
		"N":546.0,
		"O":348.0
	},
	{
		"C":"POP",
		"Y":2048,
		"N":520.0,
		"O":351.0
	},
	{
		"C":"POP",
		"Y":2049,
		"N":530.0,
		"O":354.0
	},
	{
		"C":"POP",
		"Y":2050,
		"N":502.0,
		"O":357.0
	},
	{
		"C":"AEMP",
		"Y":2019,
		"N":942.0,
		"O":304.0
	},
	{
		"C":"AEMP",
		"Y":2020,
		"N":900.0,
		"O":306.0
	},
	{
		"C":"AEMP",
		"Y":2021,
		"N":959.0,
		"O":311.0
	},
	{
		"C":"AEMP",
		"Y":2022,
		"N":1084.0,
		"O":309.0
	},
	{
		"C":"AEMP",
		"Y":2023,
		"N":1047.0,
		"O":309.0
	},
	{
		"C":"AEMP",
		"Y":2024,
		"N":1052.0,
		"O":311.0
	},
	{
		"C":"AEMP",
		"Y":2025,
		"N":1070.0,
		"O":312.0
	},
	{
		"C":"AEMP",
		"Y":2026,
		"N":1061.0,
		"O":313.0
	},
	{
		"C":"AEMP",
		"Y":2027,
		"N":1067.0,
		"O":313.0
	},
	{
		"C":"AEMP",
		"Y":2028,
		"N":1072.0,
		"O":313.0
	},
	{
		"C":"AEMP",
		"Y":2029,
		"N":1126.0,
		"O":313.0
	},
	{
		"C":"AEMP",
		"Y":2030,
		"N":1114.0,
		"O":317.0
	},
	{
		"C":"AEMP",
		"Y":2031,
		"N":1146.0,
		"O":318.0
	},
	{
		"C":"AEMP",
		"Y":2032,
		"N":1140.0,
		"O":320.0
	},
	{
		"C":"AEMP",
		"Y":2033,
		"N":1128.0,
		"O":327.0
	},
	{
		"C":"AEMP",
		"Y":2034,
		"N":1147.0,
		"O":316.0
	},
	{
		"C":"AEMP",
		"Y":2035,
		"N":1144.0,
		"O":322.0
	},
	{
		"C":"AEMP",
		"Y":2036,
		"N":1157.0,
		"O":341.0
	},
	{
		"C":"AEMP",
		"Y":2037,
		"N":1153.0,
		"O":324.0
	},
	{
		"C":"AEMP",
		"Y":2038,
		"N":1169.0,
		"O":325.0
	},
	{
		"C":"AEMP",
		"Y":2039,
		"N":1204.0,
		"O":321.0
	},
	{
		"C":"AEMP",
		"Y":2040,
		"N":1211.0,
		"O":335.0
	},
	{
		"C":"AEMP",
		"Y":2041,
		"N":1223.0,
		"O":333.0
	},
	{
		"C":"AEMP",
		"Y":2042,
		"N":1211.0,
		"O":340.0
	},
	{
		"C":"AEMP",
		"Y":2043,
		"N":1204.0,
		"O":341.0
	},
	{
		"C":"AEMP",
		"Y":2044,
		"N":1200.0,
		"O":379.0
	},
	{
		"C":"AEMP",
		"Y":2045,
		"N":1206.0,
		"O":355.0
	},
	{
		"C":"AEMP",
		"Y":2046,
		"N":1228.0,
		"O":341.0
	},
	{
		"C":"AEMP",
		"Y":2047,
		"N":1228.0,
		"O":351.0
	},
	{
		"C":"AEMP",
		"Y":2048,
		"N":1296.0,
		"O":341.0
	},
	{
		"C":"AEMP",
		"Y":2049,
		"N":1289.0,
		"O":352.0
	},
	{
		"C":"AEMP",
		"Y":2050,
		"N":1360.0,
		"O":343.0
	},
	{
		"C":"RTL",
		"Y":2019,
		"N":131.0,
		"O":113.0
	},
	{
		"C":"RTL",
		"Y":2020,
		"N":122.0,
		"O":113.0
	},
	{
		"C":"RTL",
		"Y":2021,
		"N":130.0,
		"O":113.0
	},
	{
		"C":"RTL",
		"Y":2022,
		"N":131.0,
		"O":113.0
	},
	{
		"C":"RTL",
		"Y":2023,
		"N":129.0,
		"O":114.0
	},
	{
		"C":"RTL",
		"Y":2024,
		"N":127.0,
		"O":114.0
	},
	{
		"C":"RTL",
		"Y":2025,
		"N":130.0,
		"O":114.0
	},
	{
		"C":"RTL",
		"Y":2026,
		"N":131.0,
		"O":114.0
	},
	{
		"C":"RTL",
		"Y":2027,
		"N":132.0,
		"O":115.0
	},
	{
		"C":"RTL",
		"Y":2028,
		"N":134.0,
		"O":116.0
	},
	{
		"C":"RTL",
		"Y":2029,
		"N":148.0,
		"O":116.0
	},
	{
		"C":"RTL",
		"Y":2030,
		"N":156.0,
		"O":116.0
	},
	{
		"C":"RTL",
		"Y":2031,
		"N":165.0,
		"O":116.0
	},
	{
		"C":"RTL",
		"Y":2032,
		"N":171.0,
		"O":116.0
	},
	{
		"C":"RTL",
		"Y":2033,
		"N":174.0,
		"O":116.0
	},
	{
		"C":"RTL",
		"Y":2034,
		"N":178.0,
		"O":116.0
	},
	{
		"C":"RTL",
		"Y":2035,
		"N":180.0,
		"O":117.0
	},
	{
		"C":"RTL",
		"Y":2036,
		"N":186.0,
		"O":117.0
	},
	{
		"C":"RTL",
		"Y":2037,
		"N":190.0,
		"O":118.0
	},
	{
		"C":"RTL",
		"Y":2038,
		"N":194.0,
		"O":118.0
	},
	{
		"C":"RTL",
		"Y":2039,
		"N":200.0,
		"O":118.0
	},
	{
		"C":"RTL",
		"Y":2040,
		"N":203.0,
		"O":119.0
	},
	{
		"C":"RTL",
		"Y":2041,
		"N":204.0,
		"O":120.0
	},
	{
		"C":"RTL",
		"Y":2042,
		"N":206.0,
		"O":121.0
	},
	{
		"C":"RTL",
		"Y":2043,
		"N":206.0,
		"O":121.0
	},
	{
		"C":"RTL",
		"Y":2044,
		"N":207.0,
		"O":122.0
	},
	{
		"C":"RTL",
		"Y":2045,
		"N":208.0,
		"O":122.0
	},
	{
		"C":"RTL",
		"Y":2046,
		"N":207.0,
		"O":120.0
	},
	{
		"C":"RTL",
		"Y":2047,
		"N":210.0,
		"O":121.0
	},
	{
		"C":"RTL",
		"Y":2048,
		"N":230.0,
		"O":122.0
	},
	{
		"C":"RTL",
		"Y":2049,
		"N":243.0,
		"O":122.0
	},
	{
		"C":"RTL",
		"Y":2050,
		"N":259.0,
		"O":120.0
	},
	{
		"C":"IND",
		"Y":2019,
		"N":41.0,
		"O":13.0
	},
	{
		"C":"IND",
		"Y":2020,
		"N":43.0,
		"O":13.0
	},
	{
		"C":"IND",
		"Y":2021,
		"N":43.0,
		"O":13.0
	},
	{
		"C":"IND",
		"Y":2022,
		"N":44.0,
		"O":13.0
	},
	{
		"C":"IND",
		"Y":2023,
		"N":44.0,
		"O":13.0
	},
	{
		"C":"IND",
		"Y":2024,
		"N":44.0,
		"O":13.0
	},
	{
		"C":"IND",
		"Y":2025,
		"N":43.0,
		"O":13.0
	},
	{
		"C":"IND",
		"Y":2026,
		"N":43.0,
		"O":13.0
	},
	{
		"C":"IND",
		"Y":2027,
		"N":43.0,
		"O":13.0
	},
	{
		"C":"IND",
		"Y":2028,
		"N":43.0,
		"O":13.0
	},
	{
		"C":"IND",
		"Y":2029,
		"N":43.0,
		"O":13.0
	},
	{
		"C":"IND",
		"Y":2030,
		"N":43.0,
		"O":13.0
	},
	{
		"C":"IND",
		"Y":2031,
		"N":43.0,
		"O":13.0
	},
	{
		"C":"IND",
		"Y":2032,
		"N":42.0,
		"O":13.0
	},
	{
		"C":"IND",
		"Y":2033,
		"N":42.0,
		"O":13.0
	},
	{
		"C":"IND",
		"Y":2034,
		"N":41.0,
		"O":13.0
	},
	{
		"C":"IND",
		"Y":2035,
		"N":40.0,
		"O":13.0
	},
	{
		"C":"IND",
		"Y":2036,
		"N":40.0,
		"O":13.0
	},
	{
		"C":"IND",
		"Y":2037,
		"N":40.0,
		"O":13.0
	},
	{
		"C":"IND",
		"Y":2038,
		"N":40.0,
		"O":13.0
	},
	{
		"C":"IND",
		"Y":2039,
		"N":40.0,
		"O":13.0
	},
	{
		"C":"IND",
		"Y":2040,
		"N":39.0,
		"O":13.0
	},
	{
		"C":"IND",
		"Y":2041,
		"N":38.0,
		"O":13.0
	},
	{
		"C":"IND",
		"Y":2042,
		"N":38.0,
		"O":13.0
	},
	{
		"C":"IND",
		"Y":2043,
		"N":37.0,
		"O":13.0
	},
	{
		"C":"IND",
		"Y":2044,
		"N":37.0,
		"O":13.0
	},
	{
		"C":"IND",
		"Y":2045,
		"N":37.0,
		"O":13.0
	},
	{
		"C":"IND",
		"Y":2046,
		"N":36.0,
		"O":13.0
	},
	{
		"C":"IND",
		"Y":2047,
		"N":35.0,
		"O":13.0
	},
	{
		"C":"IND",
		"Y":2048,
		"N":34.0,
		"O":13.0
	},
	{
		"C":"IND",
		"Y":2049,
		"N":34.0,
		"O":13.0
	},
	{
		"C":"IND",
		"Y":2050,
		"N":34.0,
		"O":13.0
	},
	{
		"C":"OTHR",
		"Y":2019,
		"N":726.0,
		"O":168.0
	},
	{
		"C":"OTHR",
		"Y":2020,
		"N":686.0,
		"O":168.0
	},
	{
		"C":"OTHR",
		"Y":2021,
		"N":739.0,
		"O":169.0
	},
	{
		"C":"OTHR",
		"Y":2022,
		"N":828.0,
		"O":170.0
	},
	{
		"C":"OTHR",
		"Y":2023,
		"N":833.0,
		"O":170.0
	},
	{
		"C":"OTHR",
		"Y":2024,
		"N":837.0,
		"O":171.0
	},
	{
		"C":"OTHR",
		"Y":2025,
		"N":836.0,
		"O":171.0
	},
	{
		"C":"OTHR",
		"Y":2026,
		"N":840.0,
		"O":172.0
	},
	{
		"C":"OTHR",
		"Y":2027,
		"N":845.0,
		"O":172.0
	},
	{
		"C":"OTHR",
		"Y":2028,
		"N":847.0,
		"O":173.0
	},
	{
		"C":"OTHR",
		"Y":2029,
		"N":862.0,
		"O":173.0
	},
	{
		"C":"OTHR",
		"Y":2030,
		"N":866.0,
		"O":173.0
	},
	{
		"C":"OTHR",
		"Y":2031,
		"N":869.0,
		"O":173.0
	},
	{
		"C":"OTHR",
		"Y":2032,
		"N":857.0,
		"O":174.0
	},
	{
		"C":"OTHR",
		"Y":2033,
		"N":858.0,
		"O":174.0
	},
	{
		"C":"OTHR",
		"Y":2034,
		"N":859.0,
		"O":174.0
	},
	{
		"C":"OTHR",
		"Y":2035,
		"N":845.0,
		"O":175.0
	},
	{
		"C":"OTHR",
		"Y":2036,
		"N":852.0,
		"O":175.0
	},
	{
		"C":"OTHR",
		"Y":2037,
		"N":861.0,
		"O":176.0
	},
	{
		"C":"OTHR",
		"Y":2038,
		"N":873.0,
		"O":177.0
	},
	{
		"C":"OTHR",
		"Y":2039,
		"N":887.0,
		"O":179.0
	},
	{
		"C":"OTHR",
		"Y":2040,
		"N":899.0,
		"O":182.0
	},
	{
		"C":"OTHR",
		"Y":2041,
		"N":891.0,
		"O":185.0
	},
	{
		"C":"OTHR",
		"Y":2042,
		"N":895.0,
		"O":188.0
	},
	{
		"C":"OTHR",
		"Y":2043,
		"N":885.0,
		"O":189.0
	},
	{
		"C":"OTHR",
		"Y":2044,
		"N":887.0,
		"O":190.0
	},
	{
		"C":"OTHR",
		"Y":2045,
		"N":889.0,
		"O":191.0
	},
	{
		"C":"OTHR",
		"Y":2046,
		"N":879.0,
		"O":190.0
	},
	{
		"C":"OTHR",
		"Y":2047,
		"N":878.0,
		"O":190.0
	},
	{
		"C":"OTHR",
		"Y":2048,
		"N":910.0,
		"O":190.0
	},
	{
		"C":"OTHR",
		"Y":2049,
		"N":924.0,
		"O":190.0
	},
	{
		"C":"OTHR",
		"Y":2050,
		"N":960.0,
		"O":188.0
	},
	{
		"C":"TPCL",
		"Y":2019,
		"N":898.0,
		"O":294.0
	},
	{
		"C":"TPCL",
		"Y":2020,
		"N":851.0,
		"O":294.0
	},
	{
		"C":"TPCL",
		"Y":2021,
		"N":912.0,
		"O":294.0
	},
	{
		"C":"TPCL",
		"Y":2022,
		"N":1003.0,
		"O":295.0
	},
	{
		"C":"TPCL",
		"Y":2023,
		"N":1006.0,
		"O":297.0
	},
	{
		"C":"TPCL",
		"Y":2024,
		"N":1008.0,
		"O":297.0
	},
	{
		"C":"TPCL",
		"Y":2025,
		"N":1009.0,
		"O":298.0
	},
	{
		"C":"TPCL",
		"Y":2026,
		"N":1014.0,
		"O":299.0
	},
	{
		"C":"TPCL",
		"Y":2027,
		"N":1020.0,
		"O":300.0
	},
	{
		"C":"TPCL",
		"Y":2028,
		"N":1024.0,
		"O":301.0
	},
	{
		"C":"TPCL",
		"Y":2029,
		"N":1054.0,
		"O":302.0
	},
	{
		"C":"TPCL",
		"Y":2030,
		"N":1066.0,
		"O":302.0
	},
	{
		"C":"TPCL",
		"Y":2031,
		"N":1076.0,
		"O":302.0
	},
	{
		"C":"TPCL",
		"Y":2032,
		"N":1070.0,
		"O":303.0
	},
	{
		"C":"TPCL",
		"Y":2033,
		"N":1073.0,
		"O":303.0
	},
	{
		"C":"TPCL",
		"Y":2034,
		"N":1078.0,
		"O":303.0
	},
	{
		"C":"TPCL",
		"Y":2035,
		"N":1065.0,
		"O":304.0
	},
	{
		"C":"TPCL",
		"Y":2036,
		"N":1078.0,
		"O":306.0
	},
	{
		"C":"TPCL",
		"Y":2037,
		"N":1091.0,
		"O":307.0
	},
	{
		"C":"TPCL",
		"Y":2038,
		"N":1107.0,
		"O":308.0
	},
	{
		"C":"TPCL",
		"Y":2039,
		"N":1126.0,
		"O":310.0
	},
	{
		"C":"TPCL",
		"Y":2040,
		"N":1142.0,
		"O":313.0
	},
	{
		"C":"TPCL",
		"Y":2041,
		"N":1133.0,
		"O":318.0
	},
	{
		"C":"TPCL",
		"Y":2042,
		"N":1138.0,
		"O":322.0
	},
	{
		"C":"TPCL",
		"Y":2043,
		"N":1127.0,
		"O":323.0
	},
	{
		"C":"TPCL",
		"Y":2044,
		"N":1131.0,
		"O":325.0
	},
	{
		"C":"TPCL",
		"Y":2045,
		"N":1134.0,
		"O":327.0
	},
	{
		"C":"TPCL",
		"Y":2046,
		"N":1122.0,
		"O":324.0
	},
	{
		"C":"TPCL",
		"Y":2047,
		"N":1123.0,
		"O":324.0
	},
	{
		"C":"TPCL",
		"Y":2048,
		"N":1174.0,
		"O":325.0
	},
	{
		"C":"TPCL",
		"Y":2049,
		"N":1200.0,
		"O":326.0
	},
	{
		"C":"TPCL",
		"Y":2050,
		"N":1253.0,
		"O":322.0
	},
	{
		"C":"HJI",
		"Y":2019,
		"N":1064.0,
		"O":534.0
	},
	{
		"C":"HJI",
		"Y":2020,
		"N":1020.0,
		"O":535.0
	},
	{
		"C":"HJI",
		"Y":2021,
		"N":1084.0,
		"O":537.0
	},
	{
		"C":"HJI",
		"Y":2022,
		"N":1179.0,
		"O":538.0
	},
	{
		"C":"HJI",
		"Y":2023,
		"N":1185.0,
		"O":541.0
	},
	{
		"C":"HJI",
		"Y":2024,
		"N":1189.0,
		"O":543.0
	},
	{
		"C":"HJI",
		"Y":2025,
		"N":1193.0,
		"O":544.0
	},
	{
		"C":"HJI",
		"Y":2026,
		"N":1200.0,
		"O":546.0
	},
	{
		"C":"HJI",
		"Y":2027,
		"N":1207.0,
		"O":548.0
	},
	{
		"C":"HJI",
		"Y":2028,
		"N":1211.0,
		"O":550.0
	},
	{
		"C":"HJI",
		"Y":2029,
		"N":1242.0,
		"O":551.0
	},
	{
		"C":"HJI",
		"Y":2030,
		"N":1255.0,
		"O":552.0
	},
	{
		"C":"HJI",
		"Y":2031,
		"N":1276.0,
		"O":553.0
	},
	{
		"C":"HJI",
		"Y":2032,
		"N":1290.0,
		"O":553.0
	},
	{
		"C":"HJI",
		"Y":2033,
		"N":1302.0,
		"O":555.0
	},
	{
		"C":"HJI",
		"Y":2034,
		"N":1327.0,
		"O":557.0
	},
	{
		"C":"HJI",
		"Y":2035,
		"N":1340.0,
		"O":560.0
	},
	{
		"C":"HJI",
		"Y":2036,
		"N":1371.0,
		"O":562.0
	},
	{
		"C":"HJI",
		"Y":2037,
		"N":1399.0,
		"O":562.0
	},
	{
		"C":"HJI",
		"Y":2038,
		"N":1428.0,
		"O":566.0
	},
	{
		"C":"HJI",
		"Y":2039,
		"N":1456.0,
		"O":571.0
	},
	{
		"C":"HJI",
		"Y":2040,
		"N":1483.0,
		"O":576.0
	},
	{
		"C":"HJI",
		"Y":2041,
		"N":1499.0,
		"O":582.0
	},
	{
		"C":"HJI",
		"Y":2042,
		"N":1521.0,
		"O":587.0
	},
	{
		"C":"HJI",
		"Y":2043,
		"N":1531.0,
		"O":590.0
	},
	{
		"C":"HJI",
		"Y":2044,
		"N":1546.0,
		"O":593.0
	},
	{
		"C":"HJI",
		"Y":2045,
		"N":1557.0,
		"O":593.0
	},
	{
		"C":"HJI",
		"Y":2046,
		"N":1524.0,
		"O":593.0
	},
	{
		"C":"HJI",
		"Y":2047,
		"N":1540.0,
		"O":596.0
	},
	{
		"C":"HJI",
		"Y":2048,
		"N":1569.0,
		"O":599.0
	},
	{
		"C":"HJI",
		"Y":2049,
		"N":1605.0,
		"O":601.0
	},
	{
		"C":"HJI",
		"Y":2050,
		"N":1634.0,
		"O":600.0
	}
]
